jsonchick/__init__.py
jsonchick/jsonchick.py
jsonchick-0.0.2.dist-info/LICENSE
jsonchick-0.0.2.dist-info/METADATA
jsonchick-0.0.2.dist-info/WHEEL
jsonchick-0.0.2.dist-info/top_level.txt
jsonchick-0.0.2.dist-info/RECORD
