Metadata-Version: 2.1
Name: jsonchick
Version: 0.0.2
Summary: Find JSON data paths by value
Home-page: https://github.com/andrkhar/jsonchick
Author: Andrei Kharchenko
License: UNKNOWN
Platform: UNKNOWN
Classifier: Programming Language :: Python :: 3
Classifier: License :: OSI Approved :: MIT License
Classifier: Operating System :: OS Independent
Requires-Python: >=3.6
License-File: LICENSE
